{
  "hash": "e6e1e1b4",
  "browserHash": "42c39531",
  "optimized": {
    "react": {
      "src": "../../node_modules/react/index.js",
      "file": "react.js",
      "fileHash": "374eaa41",
      "needsInterop": true
    },
    "react-dom/client": {
      "src": "../../node_modules/react-dom/client.js",
      "file": "react-dom_client.js",
      "fileHash": "dd72140e",
      "needsInterop": true
    },
    "react-router-dom": {
      "src": "../../node_modules/react-router-dom/dist/index.js",
      "file": "react-router-dom.js",
      "fileHash": "87dec949",
      "needsInterop": false
    },
    "@mui/material": {
      "src": "../../node_modules/@mui/material/index.js",
      "file": "@mui_material.js",
      "fileHash": "f381e789",
      "needsInterop": false
    },
    "react-router": {
      "src": "../../node_modules/react-router/dist/index.js",
      "file": "react-router.js",
      "fileHash": "9c8fad08",
      "needsInterop": false
    },
    "@mui/material/": {
      "src": "../../node_modules/@mui/material/index.js",
      "file": "@mui_material_.js",
      "fileHash": "ffd71cd5",
      "needsInterop": false
    },
    "@mui/material/styles": {
      "src": "../../node_modules/@mui/material/styles/index.js",
      "file": "@mui_material_styles.js",
      "fileHash": "33e81a2d",
      "needsInterop": false
    },
    "@mui/system": {
      "src": "../../node_modules/@mui/system/esm/index.js",
      "file": "@mui_system.js",
      "fileHash": "c5300a2f",
      "needsInterop": false
    }
  },
  "chunks": {
    "chunk-7MXD6AJL": {
      "file": "chunk-7MXD6AJL.js"
    },
    "chunk-J4DBJACV": {
      "file": "chunk-J4DBJACV.js"
    },
    "chunk-X6XVNPPU": {
      "file": "chunk-X6XVNPPU.js"
    },
    "chunk-JXD2HPWI": {
      "file": "chunk-JXD2HPWI.js"
    },
    "chunk-MKHZ424I": {
      "file": "chunk-MKHZ424I.js"
    },
    "chunk-BHZAVQOK": {
      "file": "chunk-BHZAVQOK.js"
    }
  }
}
